cyta/__init__.py
cyta-0.2.3.dist-info/licenses/LICENSE
cyta-0.2.3.dist-info/METADATA
cyta-0.2.3.dist-info/WHEEL
cyta-0.2.3.dist-info/entry_points.txt
cyta-0.2.3.dist-info/top_level.txt
cyta-0.2.3.dist-info/RECORD
