Metadata-Version: 2.4
Name: cyta
Version: 0.2.3
Summary: cython -a for terminal (no HTML/browser needed)
License-Expression: MIT
Project-URL: Homepage, https://github.com/cemrehancavdar/cyta
Project-URL: Repository, https://github.com/cemrehancavdar/cyta
Keywords: cython,annotation,terminal,performance
Classifier: Development Status :: 4 - Beta
Classifier: Environment :: Console
Classifier: Intended Audience :: Developers
Classifier: Programming Language :: Python :: 3
Classifier: Programming Language :: Python :: 3.9
Classifier: Programming Language :: Python :: 3.10
Classifier: Programming Language :: Python :: 3.11
Classifier: Programming Language :: Python :: 3.12
Classifier: Programming Language :: Python :: 3.13
Classifier: Programming Language :: Cython
Classifier: Topic :: Software Development :: Quality Assurance
Requires-Python: >=3.9
License-File: LICENSE
Requires-Dist: cython>=3.0.0
Requires-Dist: rich>=13.0.0
Dynamic: license-file
